PyIPM.py
PyIPM-2.0.dist-info/LICENSE
PyIPM-2.0.dist-info/METADATA
PyIPM-2.0.dist-info/WHEEL
PyIPM-2.0.dist-info/top_level.txt
PyIPM-2.0.dist-info/RECORD
