Metadata-Version: 1.2
Name: PyIPM
Version: 2.0
Summary: Interval Predictor Models in Python
Home-page: https://github.com/JCSadeghi/PyIPM/
Author: Jonathan Sadeghi
Author-email: J.C.Sadeghi@liverpool.ac.uk
License: LGPL-3.0 License
Platform: UNKNOWN
Requires-Python: >=3.7
